[
  {
    "ContainingType": "noeTaskManagerService.Controllers.AuthController",
    "Method": "SignIn",
    "RelativePath": "api/Auth/signin",
    "HttpMethod": "POST",
    "IsController": true,
    "Order": 0,
    "Parameters": [
      {
        "Name": "userCred",
        "Type": "noeTaskManagerService.Models.Auth.SignInObject",
        "IsRequired": true
      }
    ],
    "ReturnTypes": []
  },
  {
    "ContainingType": "noeTaskManagerService.Controllers.AuthController",
    "Method": "SignUp",
    "RelativePath": "api/Auth/signup",
    "HttpMethod": "POST",
    "IsController": true,
    "Order": 0,
    "Parameters": [
      {
        "Name": "userCred",
        "Type": "noeTaskManagerService.Models.Auth.SignUpObject",
        "IsRequired": true
      }
    ],
    "ReturnTypes": []
  },
  {
    "ContainingType": "noeTaskManagerService.Controllers.CreateTask",
    "Method": "Create",
    "RelativePath": "api/CreateTask",
    "HttpMethod": "POST",
    "IsController": true,
    "Order": 0,
    "Parameters": [
      {
        "Name": "newTask",
        "Type": "noeTaskManagerService.Controllers.CreateTask\u002BCreateTasksRequest",
        "IsRequired": true
      }
    ],
    "ReturnTypes": []
  },
  {
    "ContainingType": "noeTaskManagerService.Controllers.DeleteTask",
    "Method": "DeleteATask",
    "RelativePath": "api/DeleteTask/deleteByKey/{taskKey}",
    "HttpMethod": "DELETE",
    "IsController": true,
    "Order": 0,
    "Parameters": [
      {
        "Name": "taskKey",
        "Type": "System.String",
        "IsRequired": true
      }
    ],
    "ReturnTypes": []
  },
  {
    "ContainingType": "noeTaskManagerService.Controllers.GetTask",
    "Method": "All",
    "RelativePath": "api/GetTask/all",
    "HttpMethod": "GET",
    "IsController": true,
    "Order": 0,
    "Parameters": [],
    "ReturnTypes": []
  },
  {
    "ContainingType": "noeTaskManagerService.Controllers.MutateTask",
    "Method": "PatchByDescription",
    "RelativePath": "api/MutateTask/description",
    "HttpMethod": "PATCH",
    "IsController": true,
    "Order": 0,
    "Parameters": [
      {
        "Name": "mutatorRequest",
        "Type": "noeTaskManagerService.Controllers.MutateTask\u002BMutatorRequest",
        "IsRequired": true
      }
    ],
    "ReturnTypes": []
  },
  {
    "ContainingType": "noeTaskManagerService.Controllers.MutateTask",
    "Method": "PatchByDueDate",
    "RelativePath": "api/MutateTask/dueDate",
    "HttpMethod": "PATCH",
    "IsController": true,
    "Order": 0,
    "Parameters": [
      {
        "Name": "mutatorRequest",
        "Type": "noeTaskManagerService.Controllers.MutateTask\u002BMutatorRequest",
        "IsRequired": true
      }
    ],
    "ReturnTypes": []
  },
  {
    "ContainingType": "noeTaskManagerService.Controllers.MutateTask",
    "Method": "PatchByPriority",
    "RelativePath": "api/MutateTask/priority",
    "HttpMethod": "PATCH",
    "IsController": true,
    "Order": 0,
    "Parameters": [
      {
        "Name": "mutatorRequest",
        "Type": "noeTaskManagerService.Controllers.MutateTask\u002BMutatorRequest",
        "IsRequired": true
      }
    ],
    "ReturnTypes": []
  },
  {
    "ContainingType": "noeTaskManagerService.Controllers.MutateTask",
    "Method": "PatchBySummary",
    "RelativePath": "api/MutateTask/summary",
    "HttpMethod": "PATCH",
    "IsController": true,
    "Order": 0,
    "Parameters": [
      {
        "Name": "mutatorRequest",
        "Type": "noeTaskManagerService.Controllers.MutateTask\u002BMutatorRequest",
        "IsRequired": true
      }
    ],
    "ReturnTypes": []
  }
]